{
  "The Frog King, or Iron Henry": "http://www.cs.cmu.edu/~spok/grimmtmp/001.txt" ,
  "Our Lady's Child": "http://www.cs.cmu.edu/~spok/grimmtmp/002.txt" ,
  "The Story of a Youth Who Went Forth to Learn What Fear Was": "http://www.cs.cmu.edu/~spok/grimmtmp/003.txt" ,
  "The Wolf and the Seven Little Kids": "http://www.cs.cmu.edu/~spok/grimmtmp/004.txt" ,
  "Faithful John": "http://www.cs.cmu.edu/~spok/grimmtmp/005.txt" ,
  "The Good Bargain": "http://www.cs.cmu.edu/~spok/grimmtmp/006.txt" ,
  "The Twelve Brothers": "http://www.cs.cmu.edu/~spok/grimmtmp/007.txt" ,
  "Brother and Sister": "http://www.cs.cmu.edu/~spok/grimmtmp/008.txt" ,
  "Rapunzel": "http://www.cs.cmu.edu/~spok/grimmtmp/009.txt" ,
  "The Three Little Men in the Wood": "http://www.cs.cmu.edu/~spok/grimmtmp/010.txt" ,
  "The Three Spinners": "http://www.cs.cmu.edu/~spok/grimmtmp/011.txt" ,
  "Hansel and Grethel</A> (called Gretel in this vers": "http://www.cs.cmu.edu/~spok/grimmtmp/012.txt" ,
  "The Three Snake-Leaves": "http://www.cs.cmu.edu/~spok/grimmtmp/013.txt" ,
  "The White Snake": "http://www.cs.cmu.edu/~spok/grimmtmp/014.txt" ,
  "The Valiant Little Tailor": "http://www.cs.cmu.edu/~spok/grimmtmp/015.txt" ,
  "Cinderella": "http://www.cs.cmu.edu/~spok/grimmtmp/016.txt" ,
  "The Riddle": "http://www.cs.cmu.edu/~spok/grimmtmp/017.txt" ,
  "Mother Holle": "http://www.cs.cmu.edu/~spok/grimmtmp/018.txt" ,
  "The Seven Ravens": "http://www.cs.cmu.edu/~spok/grimmtmp/019.txt" ,
  "Little Red-Cap": "http://www.cs.cmu.edu/~spok/grimmtmp/020.txt" ,
  "The Singing Bone": "http://www.cs.cmu.edu/~spok/grimmtmp/021.txt" ,
  "The Devil with the Three Golden Hairs": "http://www.cs.cmu.edu/~spok/grimmtmp/022.txt" ,
  "The Girl Without Hands": "http://www.cs.cmu.edu/~spok/grimmtmp/023.txt" ,
  "Clever Hans": "http://www.cs.cmu.edu/~spok/grimmtmp/024.txt" ,
  "The Three Languages": "http://www.cs.cmu.edu/~spok/grimmtmp/025.txt" ,
  "Clever Elsie": "http://www.cs.cmu.edu/~spok/grimmtmp/026.txt" ,
  "The Wishing-Table, The Gold-Ass, and The Cudgel in the Sack": "http://www.cs.cmu.edu/~spok/grimmtmp/027.txt" ,
  "Thumbling": "http://www.cs.cmu.edu/~spok/grimmtmp/028.txt" ,
  "The Elves (two stories)": "http://www.cs.cmu.edu/~spok/grimmtmp/029.txt" ,
  "The Robber Bridegroom": "http://www.cs.cmu.edu/~spok/grimmtmp/030.txt" ,
  "The Godfather": "http://www.cs.cmu.edu/~spok/grimmtmp/031.txt" ,
  "Frau Trude": "http://www.cs.cmu.edu/~spok/grimmtmp/032.txt" ,
  "Godfather Death": "http://www.cs.cmu.edu/~spok/grimmtmp/033.txt" ,
  "Thumbling as Journeyman": "http://www.cs.cmu.edu/~spok/grimmtmp/034.txt" ,
  "Fitcher's Bird": "http://www.cs.cmu.edu/~spok/grimmtmp/035.txt" ,
  "The Juniper-Tree": "http://www.cs.cmu.edu/~spok/grimmtmp/036.txt" ,
  "Old Sultan": "http://www.cs.cmu.edu/~spok/grimmtmp/037.txt" ,
  "The Six Swans": "http://www.cs.cmu.edu/~spok/grimmtmp/038.txt" ,
  "Little Briar-Rose": "http://www.cs.cmu.edu/~spok/grimmtmp/039.txt" ,
  "Fundevogel": "http://www.cs.cmu.edu/~spok/grimmtmp/040.txt" ,
  "King Thrushbeard": "http://www.cs.cmu.edu/~spok/grimmtmp/041.txt" ,
  "Little Snow-White": "http://www.cs.cmu.edu/~spok/grimmtmp/042.txt" ,
  "The Knapsack, The Hat, and The Horn": "http://www.cs.cmu.edu/~spok/grimmtmp/043.txt" ,
  "Rumpelstiltskin": "http://www.cs.cmu.edu/~spok/grimmtmp/044.txt" ,
  "Sweetheart Roland": "http://www.cs.cmu.edu/~spok/grimmtmp/045.txt" ,
  "The Golden Bird": "http://www.cs.cmu.edu/~spok/grimmtmp/046.txt" ,
  "The Two Brothers": "http://www.cs.cmu.edu/~spok/grimmtmp/047.txt" ,
  "The Queen Bee": "http://www.cs.cmu.edu/~spok/grimmtmp/048.txt" ,
  "The Three Feathers": "http://www.cs.cmu.edu/~spok/grimmtmp/049.txt" ,
  "The Golden Goose": "http://www.cs.cmu.edu/~spok/grimmtmp/050.txt" ,
  "Allerleirauh": "http://www.cs.cmu.edu/~spok/grimmtmp/051.txt" ,
  "The Hare's Bride": "http://www.cs.cmu.edu/~spok/grimmtmp/052.txt" ,
  "The Twelve Huntsmen": "http://www.cs.cmu.edu/~spok/grimmtmp/053.txt" ,
  "The Thief and His Master": "http://www.cs.cmu.edu/~spok/grimmtmp/054.txt" ,
  "The Three Sons of Fortune": "http://www.cs.cmu.edu/~spok/grimmtmp/055.txt" ,
  "How Six Men Got On in the World": "http://www.cs.cmu.edu/~spok/grimmtmp/056.txt" ,
  "Gossip Wolf and the Fox": "http://www.cs.cmu.edu/~spok/grimmtmp/057.txt" ,
  "The Pink": "http://www.cs.cmu.edu/~spok/grimmtmp/058.txt" ,
  "The Old Man and His Grandson": "http://www.cs.cmu.edu/~spok/grimmtmp/059.txt" ,
  "The Water-Nix": "http://www.cs.cmu.edu/~spok/grimmtmp/060.txt" ,
  "Brother Lustig": "http://www.cs.cmu.edu/~spok/grimmtmp/061.txt" ,
  "Hans in Luck": "http://www.cs.cmu.edu/~spok/grimmtmp/062.txt" ,
  "Hans Married": "http://www.cs.cmu.edu/~spok/grimmtmp/063.txt" ,
  "The Gold-Children": "http://www.cs.cmu.edu/~spok/grimmtmp/064.txt" ,
  "The Singing, Soaring Lark": "http://www.cs.cmu.edu/~spok/grimmtmp/065.txt" ,
  "The Goose-Girl": "http://www.cs.cmu.edu/~spok/grimmtmp/066.txt" ,
  "The Young Giant": "http://www.cs.cmu.edu/~spok/grimmtmp/067.txt" ,
  "The Elves</A> (another story with that ti": "http://www.cs.cmu.edu/~spok/grimmtmp/068.txt" ,
  "The King of the Golden Mountain": "http://www.cs.cmu.edu/~spok/grimmtmp/069.txt" ,
  "The Raven": "http://www.cs.cmu.edu/~spok/grimmtmp/070.txt" ,
  "The Peasant's Wise Daughter": "http://www.cs.cmu.edu/~spok/grimmtmp/071.txt" ,
  "The Three Little Birds": "http://www.cs.cmu.edu/~spok/grimmtmp/072.txt" ,
  "The Water of Life": "http://www.cs.cmu.edu/~spok/grimmtmp/073.txt" ,
  "The Spirit in the Bottle": "http://www.cs.cmu.edu/~spok/grimmtmp/074.txt" ,
  "The Devil's Sooty Brother": "http://www.cs.cmu.edu/~spok/grimmtmp/075.txt" ,
  "Bearskin": "http://www.cs.cmu.edu/~spok/grimmtmp/076.txt" ,
  "The Willow-Wren and the Bear": "http://www.cs.cmu.edu/~spok/grimmtmp/077.txt" ,
  "Sweet Porridge": "http://www.cs.cmu.edu/~spok/grimmtmp/078.txt" ,
  "Wise Folks": "http://www.cs.cmu.edu/~spok/grimmtmp/079.txt" ,
  "Stories About Snakes</A> (called paddocks in this vers": "http://www.cs.cmu.edu/~spok/grimmtmp/080.txt" ,
  "The Poor Miller's Boy and the Cat": "http://www.cs.cmu.edu/~spok/grimmtmp/081.txt" ,
  "The Two Travellers": "http://www.cs.cmu.edu/~spok/grimmtmp/082.txt" ,
  "Hans the Hedgehog": "http://www.cs.cmu.edu/~spok/grimmtmp/083.txt" ,
  "The Shroud": "http://www.cs.cmu.edu/~spok/grimmtmp/084.txt" ,
  "The Skilful Huntsman": "http://www.cs.cmu.edu/~spok/grimmtmp/085.txt" ,
  "The Two Kings' Children": "http://www.cs.cmu.edu/~spok/grimmtmp/086.txt" ,
  "The Cunning Little Tailor": "http://www.cs.cmu.edu/~spok/grimmtmp/087.txt" ,
  "The Bright Sun Brings It to Light": "http://www.cs.cmu.edu/~spok/grimmtmp/088.txt" ,
  "The Blue Light": "http://www.cs.cmu.edu/~spok/grimmtmp/089.txt" ,
  "The Wilful Child": "http://www.cs.cmu.edu/~spok/grimmtmp/090.txt" ,
  "The King's Son Who Feared Nothing": "http://www.cs.cmu.edu/~spok/grimmtmp/091.txt" ,
  "Donkey Cabbages": "http://www.cs.cmu.edu/~spok/grimmtmp/092.txt" ,
  "The Old Woman in the Wood": "http://www.cs.cmu.edu/~spok/grimmtmp/093.txt" ,
  "The Three Brothers": "http://www.cs.cmu.edu/~spok/grimmtmp/094.txt" ,
  "The Devil and His Grandmother": "http://www.cs.cmu.edu/~spok/grimmtmp/095.txt" ,
  "Ferdinand the Faithful": "http://www.cs.cmu.edu/~spok/grimmtmp/096.txt" ,
  "The Iron Stove": "http://www.cs.cmu.edu/~spok/grimmtmp/097.txt" ,
  "The Four Skilful Brothers": "http://www.cs.cmu.edu/~spok/grimmtmp/098.txt" ,
  "One-Eye, Two-Eyes, and Three-Eyes": "http://www.cs.cmu.edu/~spok/grimmtmp/099.txt" ,
  "Fair Katrinelje and Pif-Paf-Poltrie": "http://www.cs.cmu.edu/~spok/grimmtmp/100.txt" ,
  "The Shoes That Were Danced to Pieces": "http://www.cs.cmu.edu/~spok/grimmtmp/101.txt" ,
  "The Six Servants": "http://www.cs.cmu.edu/~spok/grimmtmp/102.txt" ,
  "The White Bride and the Black One": "http://www.cs.cmu.edu/~spok/grimmtmp/103.txt" ,
  "Iron John": "http://www.cs.cmu.edu/~spok/grimmtmp/104.txt" ,
  "The Three Black Princesses": "http://www.cs.cmu.edu/~spok/grimmtmp/105.txt" ,
  "Knoist and His Three Sons": "http://www.cs.cmu.edu/~spok/grimmtmp/106.txt" ,
  "The Maid of Brakel": "http://www.cs.cmu.edu/~spok/grimmtmp/107.txt" ,
  "Domestic Servants": "http://www.cs.cmu.edu/~spok/grimmtmp/108.txt" ,
  "The Lambkin and the Little Fish": "http://www.cs.cmu.edu/~spok/grimmtmp/109.txt" ,
  "Simeli Mountain": "http://www.cs.cmu.edu/~spok/grimmtmp/110.txt" ,
  "Going A-Travelling": "http://www.cs.cmu.edu/~spok/grimmtmp/111.txt" ,
  "The Donkey": "http://www.cs.cmu.edu/~spok/grimmtmp/112.txt" ,
  "The Ungrateful Son": "http://www.cs.cmu.edu/~spok/grimmtmp/113.txt" ,
  "The Turnip": "http://www.cs.cmu.edu/~spok/grimmtmp/114.txt" ,
  "The Old Man Made Young Again": "http://www.cs.cmu.edu/~spok/grimmtmp/115.txt" ,
  "The Three Sluggards": "http://www.cs.cmu.edu/~spok/grimmtmp/116.txt" ,
  "The Shepherd Boy": "http://www.cs.cmu.edu/~spok/grimmtmp/117.txt" ,
  "The Star-Money": "http://www.cs.cmu.edu/~spok/grimmtmp/118.txt" ,
  "The Stolen Farthings": "http://www.cs.cmu.edu/~spok/grimmtmp/119.txt" ,
  "Brides On Their Trial": "http://www.cs.cmu.edu/~spok/grimmtmp/120.txt" ,
  "The Sparrow and His Four Children": "http://www.cs.cmu.edu/~spok/grimmtmp/121.txt" ,
  "Snow-White and Rose-Red": "http://www.cs.cmu.edu/~spok/grimmtmp/122.txt" ,
  "The Glass Coffin": "http://www.cs.cmu.edu/~spok/grimmtmp/123.txt" ,
  "Lazy Harry": "http://www.cs.cmu.edu/~spok/grimmtmp/124.txt" ,
  "The Griffin": "http://www.cs.cmu.edu/~spok/grimmtmp/125.txt" ,
  "Strong Hans": "http://www.cs.cmu.edu/~spok/grimmtmp/126.txt" ,
  "The Hut in the Forest": "http://www.cs.cmu.edu/~spok/grimmtmp/127.txt" ,
  "The Goose-Girl at the Well": "http://www.cs.cmu.edu/~spok/grimmtmp/128.txt" ,
  "Eve's Various Children": "http://www.cs.cmu.edu/~spok/grimmtmp/129.txt" ,
  "The Nix of the Mill-Pond": "http://www.cs.cmu.edu/~spok/grimmtmp/130.txt" ,
  "The Poor Boy in the Grave": "http://www.cs.cmu.edu/~spok/grimmtmp/131.txt" ,
  "The True Sweetheart": "http://www.cs.cmu.edu/~spok/grimmtmp/132.txt" ,
  "The Spindle, The Shuttle, and The Needle": "http://www.cs.cmu.edu/~spok/grimmtmp/133.txt" ,
  "The Sea-Hare": "http://www.cs.cmu.edu/~spok/grimmtmp/134.txt" ,
  "The Master-Thief": "http://www.cs.cmu.edu/~spok/grimmtmp/135.txt" ,
  "The Drummer": "http://www.cs.cmu.edu/~spok/grimmtmp/136.txt" ,
  "The Ear of Corn": "http://www.cs.cmu.edu/~spok/grimmtmp/137.txt" ,
  "Old Rinkrank": "http://www.cs.cmu.edu/~spok/grimmtmp/138.txt" ,
  "The Crystal Ball": "http://www.cs.cmu.edu/~spok/grimmtmp/139.txt" ,
  "Maid Maleen": "http://www.cs.cmu.edu/~spok/grimmtmp/140.txt" ,
  "St. Joseph in the Forest": "http://www.cs.cmu.edu/~spok/grimmtmp/141.txt" ,
  "The Twelve Apostles": "http://www.cs.cmu.edu/~spok/grimmtmp/142.txt" ,
  "The Rose": "http://www.cs.cmu.edu/~spok/grimmtmp/143.txt" ,
  "Poverty and Humility Lead to Heaven": "http://www.cs.cmu.edu/~spok/grimmtmp/144.txt" ,
  "God's Food": "http://www.cs.cmu.edu/~spok/grimmtmp/145.txt" ,
  "The Three Green Twigs": "http://www.cs.cmu.edu/~spok/grimmtmp/146.txt" ,
  "The Aged Mother": "http://www.cs.cmu.edu/~spok/grimmtmp/147.txt" ,
  "The Hazel-Branch": "http://www.cs.cmu.edu/~spok/grimmtmp/148.txt" ,
  "Cat and Mouse in Partnership": "http://www.cs.cmu.edu/~spok/grimmtmp/149.txt" ,
  "The Wonderful Musician": "http://www.cs.cmu.edu/~spok/grimmtmp/150.txt" ,
  "The Pack of Ragamuffins": "http://www.cs.cmu.edu/~spok/grimmtmp/151.txt" ,
  "The Straw, the Coal, and the Bean": "http://www.cs.cmu.edu/~spok/grimmtmp/152.txt" ,
  "The Fisherman and His Wife": "http://www.cs.cmu.edu/~spok/grimmtmp/153.txt" ,
  "The Mouse, the Bird, and the Sausage": "http://www.cs.cmu.edu/~spok/grimmtmp/154.txt" ,
  "The Bremen Town-Musicians": "http://www.cs.cmu.edu/~spok/grimmtmp/155.txt" ,
  "The Louse and the Flea": "http://www.cs.cmu.edu/~spok/grimmtmp/156.txt" ,
  "The Tailor in Heaven": "http://www.cs.cmu.edu/~spok/grimmtmp/157.txt" ,
  "The Wedding of Mrs. Fox (two stories)": "http://www.cs.cmu.edu/~spok/grimmtmp/158.txt" ,
  "The Elves</A> (one more st": "http://www.cs.cmu.edu/~spok/grimmtmp/159.txt" ,
  "Herr Korbes": "http://www.cs.cmu.edu/~spok/grimmtmp/160.txt" ,
  "The Dog and the Sparrow": "http://www.cs.cmu.edu/~spok/grimmtmp/161.txt" ,
  "Frederick and Catherine": "http://www.cs.cmu.edu/~spok/grimmtmp/162.txt" ,
  "The Little Peasant": "http://www.cs.cmu.edu/~spok/grimmtmp/163.txt" ,
  "Jorinda and Joringel": "http://www.cs.cmu.edu/~spok/grimmtmp/164.txt" ,
  "The Wolf and the Man": "http://www.cs.cmu.edu/~spok/grimmtmp/165.txt" ,
  "The Wolf and the Fox": "http://www.cs.cmu.edu/~spok/grimmtmp/166.txt" ,
  "The Fox and the Cat": "http://www.cs.cmu.edu/~spok/grimmtmp/167.txt" ,
  "Clever Grethel</A> (called Gretel in this vers": "http://www.cs.cmu.edu/~spok/grimmtmp/168.txt" ,
  "The Death of the Little Hen": "http://www.cs.cmu.edu/~spok/grimmtmp/169.txt" ,
  "Gambling Hansel": "http://www.cs.cmu.edu/~spok/grimmtmp/170.txt" ,
  "The Fox and the Geese": "http://www.cs.cmu.edu/~spok/grimmtmp/171.txt" ,
  "The Poor Man and the Rich Man": "http://www.cs.cmu.edu/~spok/grimmtmp/172.txt" ,
  "Old Hildebrand": "http://www.cs.cmu.edu/~spok/grimmtmp/173.txt" ,
  "Doctor Knowall": "http://www.cs.cmu.edu/~spok/grimmtmp/174.txt" ,
  "The Jew Among Thorns": "http://www.cs.cmu.edu/~spok/grimmtmp/175.txt" ,
  "The Flail from Heaven": "http://www.cs.cmu.edu/~spok/grimmtmp/176.txt" ,
  "The Three Army-Surgeons": "http://www.cs.cmu.edu/~spok/grimmtmp/177.txt" ,
  "The Seven Swabians": "http://www.cs.cmu.edu/~spok/grimmtmp/178.txt" ,
  "The Three Apprentices": "http://www.cs.cmu.edu/~spok/grimmtmp/179.txt" ,
  "The Lazy Spinner": "http://www.cs.cmu.edu/~spok/grimmtmp/180.txt" ,
  "The Fox and the Horse": "http://www.cs.cmu.edu/~spok/grimmtmp/181.txt" ,
  "The Lord's Animals and the Devil's": "http://www.cs.cmu.edu/~spok/grimmtmp/182.txt" ,
  "The Beam": "http://www.cs.cmu.edu/~spok/grimmtmp/183.txt" ,
  "The Old Beggar-Woman": "http://www.cs.cmu.edu/~spok/grimmtmp/184.txt" ,
  "Odds and Ends": "http://www.cs.cmu.edu/~spok/grimmtmp/185.txt" ,
  "The Story of Schlauraffen Land": "http://www.cs.cmu.edu/~spok/grimmtmp/186.txt" ,
  "The Ditmarsch Tale of Wonders": "http://www.cs.cmu.edu/~spok/grimmtmp/187.txt" ,
  "A Riddling Tale": "http://www.cs.cmu.edu/~spok/grimmtmp/188.txt" ,
  "The Wise Servant": "http://www.cs.cmu.edu/~spok/grimmtmp/189.txt" ,
  "The Peasant in Heaven": "http://www.cs.cmu.edu/~spok/grimmtmp/190.txt" ,
  "Lean Lisa": "http://www.cs.cmu.edu/~spok/grimmtmp/191.txt" ,
  "Sharing Joy and Sorrow": "http://www.cs.cmu.edu/~spok/grimmtmp/192.txt" ,
  "The Willow-Wren": "http://www.cs.cmu.edu/~spok/grimmtmp/193.txt" ,
  "The Sole": "http://www.cs.cmu.edu/~spok/grimmtmp/194.txt" ,
  "The Bittern and the Hoopoe": "http://www.cs.cmu.edu/~spok/grimmtmp/195.txt" ,
  "The Owl": "http://www.cs.cmu.edu/~spok/grimmtmp/196.txt" ,
  "The Moon": "http://www.cs.cmu.edu/~spok/grimmtmp/197.txt" ,
  "The Duration of Life": "http://www.cs.cmu.edu/~spok/grimmtmp/198.txt" ,
  "Death's Messengers": "http://www.cs.cmu.edu/~spok/grimmtmp/199.txt" ,
  "Master Pfriem": "http://www.cs.cmu.edu/~spok/grimmtmp/200.txt" ,
  "The Little Folks' Presents": "http://www.cs.cmu.edu/~spok/grimmtmp/201.txt" ,
  "The Giant and the Tailor": "http://www.cs.cmu.edu/~spok/grimmtmp/202.txt" ,
  "The Nail": "http://www.cs.cmu.edu/~spok/grimmtmp/203.txt" ,
  "The Hare and the Hedgehog": "http://www.cs.cmu.edu/~spok/grimmtmp/204.txt" ,
  "The Peasant and the Devil": "http://www.cs.cmu.edu/~spok/grimmtmp/205.txt" ,
  "The Crumbs on the Table": "http://www.cs.cmu.edu/~spok/grimmtmp/206.txt" ,
  "The Grave-Mound": "http://www.cs.cmu.edu/~spok/grimmtmp/207.txt" ,
  "The Boots of Buffalo-Leather": "http://www.cs.cmu.edu/~spok/grimmtmp/208.txt" ,
  "The Golden Key": "http://www.cs.cmu.edu/~spok/grimmtmp/209.txt"
}